memory_bank/.env
memory_bank/config.py
memory_bank/db_init.py
memory_bank/main.py
memory_bank/api/__init__.py
memory_bank/api/tools.py
memory_bank/data/memory_bank.db
memory_bank/database/__init__.py
memory_bank/database/database.py
memory_bank_mcp-0.0.1.dist-info/METADATA
memory_bank_mcp-0.0.1.dist-info/WHEEL
memory_bank_mcp-0.0.1.dist-info/entry_points.txt
memory_bank_mcp-0.0.1.dist-info/licenses/LICENSE
memory_bank_mcp-0.0.1.dist-info/RECORD
