Metadata-Version: 2.4
Name: memory-bank-mcp
Version: 0.0.1
Summary: A FastMCP-based service for storing and retrieving project files in a SQLite database
Project-URL: Homepage, https://github.com/banhmysuawx/memory-bank-mcp-python
Project-URL: Bug Tracker, https://github.com/banhmysuawx/memory-bank-mcp-python/issues
Author-email: Dinh Truong Quang <quangdinhvh2@gmail.com>
License: MIT
License-File: LICENSE
Classifier: Development Status :: 4 - Beta
Classifier: Intended Audience :: Developers
Classifier: License :: OSI Approved :: MIT License
Classifier: Operating System :: OS Independent
Classifier: Programming Language :: Python :: 3
Classifier: Programming Language :: Python :: 3.10
Classifier: Topic :: Software Development :: Libraries
Requires-Python: >=3.10
Requires-Dist: aiosqlite>=0.17.0
Requires-Dist: fastmcp>=2.0.0
Requires-Dist: pydantic-settings>=2.0.0
Requires-Dist: pydantic>=2.0.0
Requires-Dist: python-dotenv>=1.0.0
